asynct/__init__.py
asynct-0.0.2.dist-info/METADATA
asynct-0.0.2.dist-info/WHEEL
asynct-0.0.2.dist-info/licenses/LICENSE
asynct-0.0.2.dist-info/RECORD
