Metadata-Version: 2.1
Name: asynct
Version: 0.0.2
Summary: This package uses threading to create a simple future-like async interface for functions.
Project-URL: Homepage, https://github.com/danielFHcode/Asynct
Project-URL: Source, https://github.com/danielFHcode/Asynct
Project-URL: Issues, https://github.com/danielFHcode/Asynct/issues
Author-email: Daniel FH <danifhpublic@gmail.com>
License-File: LICENSE
Classifier: License :: OSI Approved :: MIT License
Classifier: Operating System :: OS Independent
Classifier: Programming Language :: Python :: 3
Requires-Python: >=3.7
